quickpac/__init__.py
quickpac/api_client.py
quickpac/configuration.py
quickpac/rest.py
quickpac/api/__init__.py
quickpac/api/barcode_api.py
quickpac/api/pickup_migros_api.py
quickpac/api/zip_api.py
quickpac/models/__init__.py
quickpac/models/communication.py
quickpac/models/dimensions.py
quickpac/models/generate_label_customer.py
quickpac/models/generate_label_definition.py
quickpac/models/generate_label_envelope.py
quickpac/models/generate_label_file_infos.py
quickpac/models/generate_label_request.py
quickpac/models/generate_label_response.py
quickpac/models/generate_label_response_definition.py
quickpac/models/generate_label_response_envelope.py
quickpac/models/generate_label_response_envelope_data.py
quickpac/models/generate_label_response_envelope_data_provider.py
quickpac/models/generate_label_response_envelope_data_provider_sending.py
quickpac/models/item.py
quickpac/models/item_choice_type.py
quickpac/models/label_data.py
quickpac/models/label_data_provider.py
quickpac/models/label_data_provider_sending.py
quickpac/models/label_response_item.py
quickpac/models/language.py
quickpac/models/language_code.py
quickpac/models/logo_aspect_ratio.py
quickpac/models/logo_horizontal_align.py
quickpac/models/logo_vertical_align.py
quickpac/models/message_type.py
quickpac/models/mode_type.py
quickpac/models/notification.py
quickpac/models/notification_type.py
quickpac/models/pickup_migros_callback_result_response.py
quickpac/models/pickup_migros_set_paket_status_request.py
quickpac/models/pickup_migros_set_ruecksendung.py
quickpac/models/print_addresses_type.py
quickpac/models/recipient.py
quickpac/models/service_code_attributes.py
quickpac/models/zip_all_response.py
quickpac/models/zip_is_current_response.py
quickpac/models/zip_model.py
test/__init__.py
test/test_barcode_api.py
test/test_communication.py
test/test_dimensions.py
test/test_generate_label_customer.py
test/test_generate_label_definition.py
test/test_generate_label_envelope.py
quickpac-1.0.0.dist-info/LICENSE
quickpac-1.0.0.dist-info/METADATA
quickpac-1.0.0.dist-info/WHEEL
quickpac-1.0.0.dist-info/top_level.txt
quickpac-1.0.0.dist-info/RECORD
