Metadata-Version: 2.1
Name: quickpac
Version: 1.0.0
Summary: Quickpac API
Home-page: https://api.quickpac.ch/swagger/index.html
Author: Quickpac
License: UNKNOWN
Keywords: Swagger,Quickpac,API
Platform: UNKNOWN
Classifier: Programming Language :: Python :: 3
Classifier: License :: OSI Approved :: MIT License
Classifier: Operating System :: OS Independent
Requires-Python: >=3.4
License-File: LICENSE
Requires-Dist: urllib3 (>=1.15)
Requires-Dist: six (>=1.10)
Requires-Dist: certifi
Requires-Dist: python-dateutil
